{"is_source_file": true, "format": "TypeScript", "description": "This file provides client-side security helper functions, including input sanitization, a wrapper for localStorage operations, and a stub for fetching a CSRF token.", "external_files": [], "external_methods": [], "published": ["sanitizeInput", "safeStorage", "getCsrfToken"], "classes": [], "methods": [{"name": "export function sanitizeInput(s: string): string { sanitizeInput", "description": "Sanitizes input string by removing control characters and limiting length.", "scope": "", "scopeKind": ""}, {"name": "safeStorage.get", "description": "Retrieves a value from localStorage by key, returning null if unavailable."}, {"name": "safeStorage.set", "description": "Stores a key-value pair in localStorage, with error handling."}, {"name": "safeStorage.remove", "description": "Removes an item from localStorage by key, with error handling."}, {"name": "export async function getCsrfToken(): Promise<string> { getCsrfToken", "description": "Asynchronously returns a CSRF token, currently a stub.", "scope": "", "scopeKind": ""}], "calls": ["window.localStorage.getItem", "window.localStorage.setItem", "window.localStorage.removeItem"], "search-terms": ["security helpers", "sanitizeInput", "localStorage wrapper", "getCsrfToken stub"], "state": 2, "file_id": 62, "knowledge_revision": 162, "git_revision": "", "ctags": [{"_type": "tag", "name": "getCsrfToken", "path": "/home/kavia/workspace/code-generation/socratic-learning-assistant-147382-147391/nextjs_frontend/src/lib/security.ts", "pattern": "/^export async function getCsrfToken(): Promise<string> {$/", "language": "TypeScript", "kind": "function"}, {"_type": "tag", "name": "safeStorage", "path": "/home/kavia/workspace/code-generation/socratic-learning-assistant-147382-147391/nextjs_frontend/src/lib/security.ts", "pattern": "/^export const safeStorage = {$/", "language": "TypeScript", "kind": "constant"}, {"_type": "tag", "name": "sanitizeInput", "path": "/home/kavia/workspace/code-generation/socratic-learning-assistant-147382-147391/nextjs_frontend/src/lib/security.ts", "pattern": "/^export function sanitizeInput(s: string): string {$/", "language": "TypeScript", "kind": "function"}], "hash": "5d87e161dda2ba1ec08e70bcc3c15262", "format-version": 4, "code-base-name": "nextjs_frontend", "filename": "nextjs_frontend/src/lib/security.ts", "revision_history": [{"162": ""}]}