{"is_source_file": true, "format": "TypeScript (tsx)", "description": "This file defines a React functional component called HeaderBar for a Next.js application. It renders a header with a logo, title, and navigation links including an upload button and a user avatar menu.", "external_files": ["next/link", "next/image", "./SecureAvatarMenu"], "external_methods": [], "published": [], "classes": [], "methods": [{"name": "HeaderBar", "description": "React functional component rendering header UI with logo, title, upload link, and avatar menu."}], "calls": ["Link", "Image", "SecureAvatarMenu"], "search-terms": ["HeaderBar", "Next.js Header component", "logo.svg", "SecureAvatarMenu", "react component", "tsx"], "state": 2, "file_id": 15, "knowledge_revision": 71, "git_revision": "", "revision_history": [{"34": ""}, {"71": ""}], "ctags": [], "hash": "09c7bacd881133918d541c8996b8d06a", "format-version": 4, "code-base-name": "nextjs_frontend", "filename": "nextjs_frontend/src/components/HeaderBar.tsx"}