{"is_source_file": true, "format": "TypeScript / TSX", "description": "This file defines the main page component for a Next.js application, rendering the Socratic Learning Assistant interface with a header and chat panel, utilizing imported components.", "external_files": ["@/components/AppShell", "@/components/ChatPanel"], "external_methods": [], "published": ["Home"], "classes": [], "methods": [{"name": "Home", "description": "Main React component rendering the application's homepage with layout and chat UI."}], "calls": ["AppShell", "ChatPanel"], "search-terms": ["Next.js", "React", "TypeScript", "page", "ChatPanel", "AppShell", "homepage", "learning assistant"], "state": 2, "file_id": 1, "knowledge_revision": 212, "git_revision": "a7245b195139975057632562ee4b7192fa2365d3", "revision_history": [{"16": "6c25679a414405ad44d5e6f9e4eb90bfa38f4221"}, {"22": "6c25679a414405ad44d5e6f9e4eb90bfa38f4221"}, {"182": "475a8818d45ad705e7740a5fbccd27eb0cac3e96"}, {"212": "a7245b195139975057632562ee4b7192fa2365d3"}], "ctags": [], "hash": "7a1a6008147ee98a1968990c82697a62", "format-version": 4, "code-base-name": "nextjs_frontend", "filename": "nextjs_frontend/src/app/page.tsx"}